churnzero_api_wrapper/__init__.py
churnzero_api_wrapper/client.py
churnzero_api_wrapper/logger.py
churnzero_api_wrapper-0.2.3.dist-info/LICENSE
churnzero_api_wrapper-0.2.3.dist-info/WHEEL
churnzero_api_wrapper-0.2.3.dist-info/METADATA
churnzero_api_wrapper-0.2.3.dist-info/RECORD
